<?xml version="1.0" encoding="UTF-8"?>
<service xmlns="http://zstack.org/schema/zstack">
    <id>identity</id>
    <interceptor>AccountManager</interceptor>

    <message>
        <name>org.zstack.account.header.APICreateAccountMsg</name>
    </message>

    <message>
        <name>org.zstack.account.header.APIUpdateAccountMsg</name>
    </message>

    <message>
        <name>org.zstack.account.header.identity.APILogInByAccountMsg</name>
    </message>

    <message>
        <name>org.zstack.account.header.identity.APILogInByUserMsg</name>
    </message>

    <message>
        <name>org.zstack.account.header.identity.APILogOutMsg</name>
    </message>

    <message>
        <name>org.zstack.account.header.identity.APIValidateSessionMsg</name>
    </message>

    <message>
        <name>org.zstack.header.identity.APIGetSessionPolicyMsg</name>
    </message>

    <message>
        <name>org.zstack.account.header.APICreateUserMsg</name>
    </message>

    <message>
        <name>org.zstack.account.header.APIUpdateUserMsg</name>
    </message>

    <message>
        <name>org.zstack.account.header.APIDeleteUserMsg</name>
    </message>

    <message>
        <name>org.zstack.account.header.APIQueryUserMsg</name>
        <serviceId>query</serviceId>
    </message>

    <message>
        <name>org.zstack.account.header.APIQueryAccountMsg</name>
        <serviceId>query</serviceId>
    </message>

    <message>
        <name>org.zstack.account.header.identity.APICheckApiPermissionMsg</name>
    </message>

    <message>
        <name>org.zstack.account.header.APIListAllAccountMsg</name>
    </message>

    <message>
        <name>org.zstack.account.header.APIListAllUsersMsg</name>
    </message>

    <message>
        <name>org.zstack.account.header.APIUpdateUserPWDMsg</name>
    </message>

    <message>
        <name>org.zstack.account.header.APIUpdateAccountPWDMsg</name>
    </message>
    <message>
        <name>org.zstack.account.header.APIUpdateAccountPhoneMsg</name>
    </message>
    <message>
        <name>org.zstack.account.header.APIUpdateUserPhoneMsg</name>
    </message>
    <message>
        <name>org.zstack.account.header.APIUpdateAccountEmailMsg</name>
    </message>
    <message>
        <name>org.zstack.account.header.APIUpdateUserEmailMsg</name>
    </message>
    <message>
        <name>org.zstack.account.header.APIUpdateIndustryMsg</name>
    </message>

    <message>
        <name>org.zstack.account.header.APIAttachPolicyToUserMsg</name>
    </message>

    <message>
        <name>org.zstack.account.header.APIDeletePolicyMsg</name>
    </message>

    <message>
        <name>org.zstack.account.header.APICreatePolicyMsg</name>
    </message>

    <message>
        <name>org.zstack.account.header.APIDetachPolicyFromUserMsg</name>
    </message>

    <message>
        <name>org.zstack.account.header.APICreateAuthorityMsg</name>
    </message>
    <message>
        <name>org.zstack.account.header.APIUpdateAuthorityMsg</name>
    </message>

</service>
